skywinder_analysis/__init__.py
skywinder_analysis/apps/__init__.py
skywinder_analysis/apps/file_conversion/__init__.py
skywinder_analysis/apps/file_conversion/to_netcdf/__init__.py
skywinder_analysis/apps/file_conversion/to_netcdf/convert_to_netcdf.py
skywinder_analysis/apps/file_conversion/to_netcdf/custom_settings.py
skywinder_analysis/apps/file_conversion/to_netcdf/default_settings.py
skywinder_analysis/apps/file_conversion/to_netcdf_split_into_sections/__init__.py
skywinder_analysis/apps/file_conversion/to_netcdf_split_into_sections/convert_to_netcdf_in_sections.py
skywinder_analysis/apps/file_conversion/to_netcdf_split_into_sections/custom_settings.py
skywinder_analysis/apps/file_conversion/to_netcdf_split_into_sections/default_settings.py
skywinder_analysis/apps/jitter_analysis/__init__.py
skywinder_analysis/apps/jitter_analysis/lomb_scargle_periodogram/__init__.py
skywinder_analysis/apps/jitter_analysis/lomb_scargle_periodogram/custom_settings.py
skywinder_analysis/apps/jitter_analysis/lomb_scargle_periodogram/default_settings.py
skywinder_analysis/apps/jitter_analysis/lomb_scargle_periodogram/lomb_scargle_periodogram.py
skywinder_analysis/apps/movie_making/__init__.py
skywinder_analysis/apps/movie_making/basic_make_movie/__init__.py
skywinder_analysis/apps/movie_making/basic_make_movie/_custom_settings.py
skywinder_analysis/apps/movie_making/basic_make_movie/custom_settings.py
skywinder_analysis/apps/movie_making/basic_make_movie/default_settings.py
skywinder_analysis/apps/movie_making/basic_make_movie/make_movie.py
skywinder_analysis/apps/movie_making/feature_and_context/__init__.py
skywinder_analysis/apps/movie_making/feature_and_context/custom_settings.py
skywinder_analysis/apps/movie_making/feature_and_context/default_settings.py
skywinder_analysis/apps/movie_making/feature_and_context/feature_and_context.py
skywinder_analysis/apps/movie_making/make_movie_rolling_flat_field/__init__.py
SkyWinder_Analysis-0.0.2.dist-info/LICENSE
SkyWinder_Analysis-0.0.2.dist-info/METADATA
SkyWinder_Analysis-0.0.2.dist-info/WHEEL
SkyWinder_Analysis-0.0.2.dist-info/top_level.txt
SkyWinder_Analysis-0.0.2.dist-info/RECORD
