Metadata-Version: 2.1
Name: SkyWinder-Analysis
Version: 0.0.2
Summary: A package for image analysis for aeronomy experiments
Home-page: https://github.com/PolarMesosphericClouds/SkyWinder-Analysis
Author: Carl Bjorn Kjellstrand
Author-email: bkjell@gmail.com
Classifier: Programming Language :: Python :: 3
Classifier: License :: OSI Approved :: BSD License
Classifier: Operating System :: OS Independent
Requires-Python: >=3.6
License-File: LICENSE
